romlib/__init__.py
romlib/db.py
romlib/errors.py
romlib/roms.py
romlib/tags.py
romlib/data/gc_country.csv
romlib/data/gc_country_combinations.csv
romlib/data/gc_country_unofficial.csv
romlib/data/gc_gen.csv
romlib/data/gc_nes.csv
romlib/data/gc_snes.csv
romlib/data/gc_standard.csv
romlib/data/gc_translations.csv
romlib/data/gc_universal.csv
romlib-0.2.0.dist-info/licenses/LICENSE
romlib-0.2.0.dist-info/METADATA
romlib-0.2.0.dist-info/WHEEL
romlib-0.2.0.dist-info/top_level.txt
romlib-0.2.0.dist-info/RECORD
