Metadata-Version: 2.4
Name: ROMLib
Version: 0.2.0
Summary: Librería para gestionar ROMs de 8 y 16 bits (SMD, SNES, SMS, NES)
Author-email: Juan Arbotti <juanarbotti@gmail.com>
License: GPL-3.0-only
Project-URL: Homepage, https://github.com/juanarbotti/romlib
Project-URL: Repository, https://github.com/juanarbotti/romlib
Project-URL: Issues, https://github.com/juanarbotti/romlib/issues
Classifier: Programming Language :: Python :: 3
Classifier: License :: OSI Approved :: GNU General Public License v3 (GPLv3)
Classifier: Operating System :: OS Independent
Classifier: Topic :: Software Development :: Libraries :: Python Modules
License-File: LICENSE
Requires-Dist: py7zr>=0.22.0
Requires-Dist: pycryptodomex>=3.22.0
Requires-Dist: pyzstd>=0.16.2
Requires-Dist: pybcj>=1.0.3
Requires-Dist: pyppmd>=1.1.1
Requires-Dist: inflate64>=1.0.1
Requires-Dist: multivolumefile>=0.2.3
Requires-Dist: Brotli>=1.1.0
Requires-Dist: psutil>=7.0.0
Requires-Dist: texttable>=1.7.0
Requires-Dist: packaging>=24.2
Requires-Dist: wcwidth>=0.2.13
Dynamic: license-file
